setup.py
src/megaplan/__init__.py
src/megaplan.egg-info/PKG-INFO
src/megaplan.egg-info/SOURCES.txt
src/megaplan.egg-info/dependency_links.txt
src/megaplan.egg-info/top_level.txt